hackrecon/__init__.py
hackrecon/hackrecon.py
hackrecon-1.7.dist-info/LICENSE
hackrecon-1.7.dist-info/METADATA
hackrecon-1.7.dist-info/WHEEL
hackrecon-1.7.dist-info/entry_points.txt
hackrecon-1.7.dist-info/top_level.txt
hackrecon-1.7.dist-info/RECORD
