Metadata-Version: 2.1
Name: hackrecon
Version: 1.7
Summary: Reconnaissance tool
Home-page: https://github.com/EmilienPer/HackRecon
Author: Emilien Peretti
Author-email: code@emilienperetti.be
License: AGPLv3
Platform: UNKNOWN
Requires-Dist: setuptools
Requires-Dist: enlighten
Requires-Dist: lxml
Requires-Dist: netaddr
